salgorithm/BFS.py
salgorithm/BinarySearch.py
salgorithm/Bubble.py
salgorithm/Bucket.py
salgorithm/CaesarCipher.py
salgorithm/Cocktail.py
salgorithm/DFS.py
salgorithm/Greedy.py
salgorithm/Heap.py
salgorithm/Insertion.py
salgorithm/Interpolation.py
salgorithm/Jump.py
salgorithm/Linear.py
salgorithm/Merge.py
salgorithm/Quick.py
salgorithm/RSA.py
salgorithm/Radix.py
salgorithm/Selection.py
salgorithm/Shell.py
salgorithm/Tabu.py
salgorithm/TransposeCipher.py
salgorithm/VigenereCipher.py
salgorithm/__init__.py
salgorithm-0.1.1.dist-info/LICENSE
salgorithm-0.1.1.dist-info/METADATA
salgorithm-0.1.1.dist-info/WHEEL
salgorithm-0.1.1.dist-info/top_level.txt
salgorithm-0.1.1.dist-info/RECORD
